loongfei-utils/MultiThreading.py
loongfei-utils/__init__.py
loongfei_utils/ConfigLogger.py
loongfei_utils/M3u8Crawer.py
loongfei_utils/MultiThreading.py
loongfei_utils/__init__.py
loongfei_utils/utils/LoggerUtils.py
loongfei_utils/utils/StrUtils.py
loongfei_utils/utils/__init__.py
loongfei_utils-1.0.8.dist-info/LICENSE
loongfei_utils-1.0.8.dist-info/METADATA
loongfei_utils-1.0.8.dist-info/WHEEL
loongfei_utils-1.0.8.dist-info/top_level.txt
loongfei_utils-1.0.8.dist-info/RECORD
