Metadata-Version: 2.1
Name: loongfei_utils
Version: 1.0.8
Summary: python工具包
Home-page: https://gitee.com/fcf_python/python-utils
Author: 龙飞
Author-email: fcfwork@163.com
Classifier: Programming Language :: Python :: 3
Classifier: License :: OSI Approved :: MIT License
Classifier: Operating System :: OS Independent
Requires-Python: >=3.6
License-File: LICENSE
